sf_utils/__init__.py
sf_utils/sf_utils.py
sf_utils-0.0.3.dist-info/LICENSE
sf_utils-0.0.3.dist-info/METADATA
sf_utils-0.0.3.dist-info/WHEEL
sf_utils-0.0.3.dist-info/entry_points.txt
sf_utils-0.0.3.dist-info/top_level.txt
sf_utils-0.0.3.dist-info/RECORD
