Metadata-Version: 2.1
Name: sf-utils
Version: 0.0.3
Summary: Various utilities built around sf-cli
Author-email: Aditya Raj <aditya2400raj@gmail.com>
Project-URL: Homepage, https://github.com/aditya24raj/sf_utils
Project-URL: Issues, https://github.com/aditya24raj/sf_utils/issues
Classifier: Programming Language :: Python :: 3
Classifier: License :: OSI Approved :: GNU General Public License v2 (GPLv2)
Classifier: Operating System :: OS Independent
Requires-Python: >=3.8
License-File: LICENSE
Requires-Dist: fire
